particle_tracking_manager/__init__.py
particle_tracking_manager/_version.py
particle_tracking_manager/cli.py
particle_tracking_manager/config_logging.py
particle_tracking_manager/config_misc.py
particle_tracking_manager/config_ocean_model.py
particle_tracking_manager/config_the_manager.py
particle_tracking_manager/ocean_model_registry.py
particle_tracking_manager/plotting.py
particle_tracking_manager/the_manager.py
particle_tracking_manager/models/__init__.py
particle_tracking_manager/models/opendrift/__init__.py
particle_tracking_manager/models/opendrift/config_opendrift.py
particle_tracking_manager/models/opendrift/opendrift.py
particle_tracking_manager/models/opendrift/plot.py
particle_tracking_manager/models/opendrift/utils.py
particle_tracking_manager/models/opendrift/enums/__init__.py
particle_tracking_manager/models/opendrift/enums/object_types.py
particle_tracking_manager/models/opendrift/enums/oil_types.py
particle_tracking_manager/models/opendrift/enums/others.py
particle_tracking_manager/models/opendrift/enums/species_types.py
particle_tracking_manager/ocean_models/CIOFS.yaml
particle_tracking_manager/ocean_models/CIOFS3.yaml
particle_tracking_manager/ocean_models/CIOFSFRESH.yaml
particle_tracking_manager/ocean_models/CIOFSOP.yaml
particle_tracking_manager/ocean_models/NWGOA.yaml
particle_tracking_manager/user_ocean_models/ONTHEFLY.yaml
particle_tracking_manager/user_ocean_models/TXLA.yaml
particle_tracking_manager-2.3.0.dist-info/licenses/LICENSE.txt
particle_tracking_manager-2.3.0.dist-info/METADATA
particle_tracking_manager-2.3.0.dist-info/WHEEL
particle_tracking_manager-2.3.0.dist-info/entry_points.txt
particle_tracking_manager-2.3.0.dist-info/top_level.txt
particle_tracking_manager-2.3.0.dist-info/RECORD
