Metadata-Version: 2.4
Name: particle_tracking_manager
Version: 2.3.0
Summary: Manager for particle tracking simulations.
Home-page: https://github.com/axiom-data-science/particle-tracking-manager
Author: axiom-data-science
Author-email: kristen@axds.co
License: MIT
Classifier: Development Status :: 5 - Production/Stable
Classifier: Topic :: Scientific/Engineering
Classifier: Intended Audience :: Science/Research
Classifier: Operating System :: OS Independent
Classifier: Programming Language :: Python
Classifier: Programming Language :: Python :: 3
Classifier: Programming Language :: Python :: 3.11
Classifier: Programming Language :: Python :: 3.12
Classifier: Programming Language :: Python :: 3.13
Classifier: License :: OSI Approved :: MIT License
Requires-Python: >=3.11
License-File: LICENSE.txt
Requires-Dist: adios_db
Requires-Dist: aiohttp
Requires-Dist: appdirs
Requires-Dist: dask
Requires-Dist: fastparquet
Requires-Dist: importlib_resources
Requires-Dist: kerchunk==0.2.7
Requires-Dist: matplotlib
Requires-Dist: netcdf4
Requires-Dist: numpy
Requires-Dist: opendrift
Requires-Dist: pandas
Requires-Dist: pip
Requires-Dist: pydantic
Requires-Dist: requests
Requires-Dist: scipy
Requires-Dist: xarray
Requires-Dist: zarr<3.0.0
Dynamic: license-file
